Workbook

Sheet Summary
A1: Commercial Pricing & Profitability Analytics: FY2026 Summary
A2: Synthetic B2B specialty-catalyst dataset: 40 customers, 12 products, 3 families, 24 months. Illustrative only.
A4: Announced list increase | B4: ='Price Waterfall'!B16 -> 0.05
A5: Realized invoice price change | B5: ='Price Waterfall'!B17 -> 0.037376128
A6: Realized pocket price change | B6: ='Price Waterfall'!B18 -> 0.039066398
A7: Realization rate | B7: ='Price Waterfall'!B19 -> 0.78132795
A8: Price leakage list to pocket FY26 | B8: ='Price Waterfall'!C12 -> 0.14874473
A9: Pocket revenue FY25 | B9: ='PVM Bridge'!B20 -> 1.3658746e+08
A10: Volume effect | B10: ='PVM Bridge'!B21 -> -5025707.7
A11: Mix effect | B11: ='PVM Bridge'!B22 -> 6556162.5
A12: Price effect | B12: ='PVM Bridge'!B23 -> 5395769.2
A13: Pocket revenue FY26 | B13: ='PVM Bridge'!B24 -> 1.4351368e+08
A14: Pocket margin % FY25 | B14: ='PVM Bridge'!B27 -> 0.33548424
A15: Pocket margin % FY26 | B15: ='PVM Bridge'!C27 -> 0.3501169
A16: Loss-making customers | B16: ='Customer Profitability'!H46 -> 6
A17: Customers below target margin | B17: ='Customer Profitability'!H47 -> 24
A18: Peak cumulative profit (whale curve) | B18: ='Customer Profitability'!H48 -> 1.0217315
A19: Customers to reach peak | B19: ='Customer Profitability'!H49 -> 34
A20: Profit erased by loss-makers | B20: ='Customer Profitability'!H50 -> 713196.98
A21: Avg uplift needed, below-target customers | B21: ='Customer Profitability'!H53 -> 0.15852048

Sheet Assumptions
A1: Commercial Pricing & Profitability Analytics: Assumptions
A2: Synthetic B2B catalyst dataset (illustrative only). Blue = input, black = formula, green = cross-sheet link. Yellow = key levers.
A4: FY2026 announced list price increase | B4: 0.05 | C4: Assumption: uniform list increase across all grades
A5: FY2026 standard cost inflation | B5: 0.03
A6: Cost of capital (payment-terms cost) | B6: 0.08
A7: Target customer net margin (renewal scenario) | B7: 0.25 | C7: Floor for contract renewal pricing

Sheet Products
A1: Product | B1: Family | C1: List Price FY25 ($/t) | D1: Std Cost FY25 ($/t) | E1: List Price FY26 ($/t) | F1: Std Cost FY26 ($/t)
A2: FCC-01 | B2: FCC | C2: 3270 | D2: 2190 | E2: =C2*(1+Assumptions!$B$4) -> 3433.5 | F2: =D2*(1+Assumptions!$B$5) -> 2255.7
A3: FCC-02 | B3: FCC | C3: 3700 | D3: 2400 | E3: =C3*(1+Assumptions!$B$4) -> 3885 | F3: =D3*(1+Assumptions!$B$5) -> 2472
A4: FCC-03 | B4: FCC | C4: 3530 | D4: 2410 | E4: =C4*(1+Assumptions!$B$4) -> 3706.5 | F4: =D4*(1+Assumptions!$B$5) -> 2482.3
A5: FCC-04 | B5: FCC | C5: 4360 | D5: 2770 | E5: =C5*(1+Assumptions!$B$4) -> 4578 | F5: =D5*(1+Assumptions!$B$5) -> 2853.1
A6: HYD-01 | B6: Hydroprocessing | C6: 12570 | D6: 7290 | E6: =C6*(1+Assumptions!$B$4) -> 13198.5 | F6: =D6*(1+Assumptions!$B$5) -> 7508.7
A7: HYD-02 | B7: Hydroprocessing | C7: 14770 | D7: 9480 | E7: =C7*(1+Assumptions!$B$4) -> 15508.5 | F7: =D7*(1+Assumptions!$B$5) -> 9764.4
A8: HYD-03 | B8: Hydroprocessing | C8: 12450 | D8: 7780 | E8: =C8*(1+Assumptions!$B$4) -> 13072.5 | F8: =D8*(1+Assumptions!$B$5) -> 8013.4
A9: HYD-04 | B9: Hydroprocessing | C9: 11610 | D9: 7340 | E9: =C9*(1+Assumptions!$B$4) -> 12190.5 | F9: =D9*(1+Assumptions!$B$5) -> 7560.2
A10: SPE-01 | B10: Specialty | C10: 28970 | D10: 14310 | E10: =C10*(1+Assumptions!$B$4) -> 30418.5 | F10: =D10*(1+Assumptions!$B$5) -> 14739.3
A11: SPE-02 | B11: Specialty | C11: 25560 | D11: 12250 | E11: =C11*(1+Assumptions!$B$4) -> 26838 | F11: =D11*(1+Assumptions!$B$5) -> 12617.5
A12: SPE-03 | B12: Specialty | C12: 30520 | D12: 15440 | E12: =C12*(1+Assumptions!$B$4) -> 32046 | F12: =D12*(1+Assumptions!$B$5) -> 15903.2
A13: SPE-04 | B13: Specialty | C13: 33260 | D13: 15020 | E13: =C13*(1+Assumptions!$B$4) -> 34923 | F13: =D13*(1+Assumptions!$B$5) -> 15470.6

Sheet Customers
A1: Customer | B1: Segment | C1: Tier | D1: On-Invoice Discount FY25 | E1: Discount Drift FY26 | F1: On-Invoice Discount FY26 | G1: Volume Rebate | H1: Freight ($/t) | I1: Payment Terms (days) | J1: Annual Cost-to-Serve ($)
A2: C001 | B2: Refining | C2: Core | D2: 0.072 | E2: 0.042 | F2: =D2+E2 -> 0.114 | G2: 0 | H2: 280 | I2: 60 | J2: 420000
A3: C002 | B3: Petrochemical | C3: Transactional | D3: 0.048 | E3: 0.019 | F3: =D3+E3 -> 0.067 | G3: 0.01 | H3: 390 | I3: 30 | J3: 338000
A4: C003 | B4: Specialty Chemicals | C4: Core | D4: 0.08 | E4: 0 | F4: =D4+E4 -> 0.08 | G4: 0.02 | H4: 140 | I4: 60 | J4: 519000
A5: C004 | B5: Refining | C5: Core | D5: 0.078 | E5: 0 | F5: =D5+E5 -> 0.078 | G5: 0.02 | H5: 280 | I5: 60 | J5: 301000
A6: C005 | B6: Petrochemical | C6: Core | D6: 0.08 | E6: 0 | F6: =D6+E6 -> 0.08 | G6: 0 | H6: 390 | I6: 90 | J6: 323000
A7: C006 | B7: Refining | C7: Core | D7: 0.075 | E7: 0.06 | F7: =D7+E7 -> 0.135 | G7: 0.03 | H7: 410 | I7: 90 | J7: 548000
A8: C007 | B8: Refining | C8: Core | D8: 0.067 | E8: 0 | F8: =D8+E8 -> 0.067 | G8: 0.02 | H8: 250 | I8: 30 | J8: 305000
A9: C008 | B9: Petrochemical | C9: Transactional | D9: 0.048 | E9: 0 | F9: =D9+E9 -> 0.048 | G9: 0.03 | H9: 390 | I9: 30 | J9: 404000
A10: C009 | B10: Specialty Chemicals | C10: Transactional | D10: 0.047 | E10: 0.056 | F10: =D10+E10 -> 0.103 | G10: 0.05 | H10: 160 | I10: 60 | J10: 370000
A11: C010 | B11: Refining | C11: Transactional | D11: 0.023 | E11: 0 | F11: =D11+E11 -> 0.023 | G11: 0.02 | H11: 370 | I11: 60 | J11: 237000
A12: C011 | B12: Refining | C12: Transactional | D12: 0.026 | E12: 0.017 | F12: =D12+E12 -> 0.043 | G12: 0 | H12: 90 | I12: 30 | J12: 300000
A13: C012 | B13: Specialty Chemicals | C13: Transactional | D13: 0.038 | E13: 0 | F13: =D13+E13 -> 0.038 | G13: 0.01 | H13: 190 | I13: 30 | J13: 329000
... A41: C040 | B41: Refining | C41: Transactional | D41: 0.039 | E41: 0.03 | F41: =D41+E41 -> 0.069 | G41: 0.03 | H41: 110 | I41: 90 | J41: 207000

Sheet Transactions
A1: Year | B1: Month | C1: Customer | D1: Product | E1: Family | F1: Tons | G1: List Price ($/t) | H1: On-Inv Disc | I1: Gross Revenue ($) | J1: Invoice Revenue ($) | K1: Rebates ($) | L1: Freight ($) | M1: Terms Cost ($) | N1: Pocket Revenue ($) | O1: Std COGS ($) | P1: Pocket Margin ($)
A2: 2025 | B2: 1 | C2: C001 | D2: HYD-03 | E2: =INDEX(Products!$B$2:$B$13,MATCH(D2,Products!$A$2:$A$13,0)) -> Hydroprocessing | F2: 13.9 | G2: =IF(A2="2025",INDEX(Products!$C$2:$C$13,MATCH(D2,Products!$A$2:$A$13,0)),INDEX(Products!$E$2:$E$13,MATCH(D2,Products!$A$2:$A$13,0))) -> 12450 | H2: =IF(A2="2025",INDEX(Customers!$D$2:$D$41,MATCH(C2,Customers!$A$2:$A$41,0)),INDEX(Customers!$F$2:$F$41,MATCH(C2,Customers!$A$2:$A$41,0))) -> 0.072 | I2: =F2*G2 -> 173055 | J2: =I2*(1-H2) -> 160595.04 | K2: =J2*INDEX(Customers!$G$2:$G$41,MATCH(C2,Customers!$A$2:$A$41,0)) -> 0 | L2: =F2*INDEX(Customers!$H$2:$H$41,MATCH(C2,Customers!$A$2:$A$41,0)) -> 3892 | M2: =J2*INDEX(Customers!$I$2:$I$41,MATCH(C2,Customers!$A$2:$A$41,0))/365*Assumptions!$B$6 -> 2111.9348 | N2: =J2-K2-L2-M2 -> 154591.11 | O2: =F2*IF(A2="2025",INDEX(Products!$D$2:$D$13,MATCH(D2,Products!$A$2:$A$13,0)),INDEX(Products!$F$2:$F$13,MATCH(D2,Products!$A$2:$A$13,0))) -> 108142 | P2: =N2-O2 -> 46449.105
A3: 2025 | B3: 2 | C3: C001 | D3: HYD-03 | E3: =INDEX(Products!$B$2:$B$13,MATCH(D3,Products!$A$2:$A$13,0)) -> Hydroprocessing | F3: 21.8 | G3: =IF(A3="2025",INDEX(Products!$C$2:$C$13,MATCH(D3,Products!$A$2:$A$13,0)),INDEX(Products!$E$2:$E$13,MATCH(D3,Products!$A$2:$A$13,0))) -> 12450 | H3: =IF(A3="2025",INDEX(Customers!$D$2:$D$41,MATCH(C3,Customers!$A$2:$A$41,0)),INDEX(Customers!$F$2:$F$41,MATCH(C3,Customers!$A$2:$A$41,0))) -> 0.072 | I3: =F3*G3 -> 271410 | J3: =I3*(1-H3) -> 251868.48 | K3: =J3*INDEX(Customers!$G$2:$G$41,MATCH(C3,Customers!$A$2:$A$41,0)) -> 0 | L3: =F3*INDEX(Customers!$H$2:$H$41,MATCH(C3,Customers!$A$2:$A$41,0)) -> 6104 | M3: =J3*INDEX(Customers!$I$2:$I$41,MATCH(C3,Customers!$A$2:$A$41,0))/365*Assumptions!$B$6 -> 3312.243 | N3: =J3-K3-L3-M3 -> 242452.24 | O3: =F3*IF(A3="2025",INDEX(Products!$D$2:$D$13,MATCH(D3,Products!$A$2:$A$13,0)),INDEX(Products!$F$2:$F$13,MATCH(D3,Products!$A$2:$A$13,0))) -> 169604 | P3: =N3-O3 -> 72848.237
A4: 2025 | B4: 3 | C4: C001 | D4: HYD-03 | E4: =INDEX(Products!$B$2:$B$13,MATCH(D4,Products!$A$2:$A$13,0)) -> Hydroprocessing | F4: 16.1 | G4: =IF(A4="2025",INDEX(Products!$C$2:$C$13,MATCH(D4,Products!$A$2:$A$13,0)),INDEX(Products!$E$2:$E$13,MATCH(D4,Products!$A$2:$A$13,0))) -> 12450 | H4: =IF(A4="2025",INDEX(Customers!$D$2:$D$41,MATCH(C4,Customers!$A$2:$A$41,0)),INDEX(Customers!$F$2:$F$41,MATCH(C4,Customers!$A$2:$A$41,0))) -> 0.072 | I4: =F4*G4 -> 200445 | J4: =I4*(1-H4) -> 186012.96 | K4: =J4*INDEX(Customers!$G$2:$G$41,MATCH(C4,Customers!$A$2:$A$41,0)) -> 0 | L4: =F4*INDEX(Customers!$H$2:$H$41,MATCH(C4,Customers!$A$2:$A$41,0)) -> 4508 | M4: =J4*INDEX(Customers!$I$2:$I$41,MATCH(C4,Customers!$A$2:$A$41,0))/365*Assumptions!$B$6 -> 2446.1978 | N4: =J4-K4-L4-M4 -> 179058.76 | O4: =F4*IF(A4="2025",INDEX(Products!$D$2:$D$13,MATCH(D4,Products!$A$2:$A$13,0)),INDEX(Products!$F$2:$F$13,MATCH(D4,Products!$A$2:$A$13,0))) -> 125258 | P4: =N4-O4 -> 53800.762
A5: 2025 | B5: 4 | C5: C001 | D5: HYD-03 | E5: =INDEX(Products!$B$2:$B$13,MATCH(D5,Products!$A$2:$A$13,0)) -> Hydroprocessing | F5: 14.8 | G5: =IF(A5="2025",INDEX(Products!$C$2:$C$13,MATCH(D5,Products!$A$2:$A$13,0)),INDEX(Products!$E$2:$E$13,MATCH(D5,Products!$A$2:$A$13,0))) -> 12450 | H5: =IF(A5="2025",INDEX(Customers!$D$2:$D$41,MATCH(C5,Customers!$A$2:$A$41,0)),INDEX(Customers!$F$2:$F$41,MATCH(C5,Customers!$A$2:$A$41,0))) -> 0.072 | I5: =F5*G5 -> 184260 | J5: =I5*(1-H5) -> 170993.28 | K5: =J5*INDEX(Customers!$G$2:$G$41,MATCH(C5,Customers!$A$2:$A$41,0)) -> 0 | L5: =F5*INDEX(Customers!$H$2:$H$41,MATCH(C5,Customers!$A$2:$A$41,0)) -> 4144 | M5: =J5*INDEX(Customers!$I$2:$I$41,MATCH(C5,Customers!$A$2:$A$41,0))/365*Assumptions!$B$6 -> 2248.6788 | N5: =J5-K5-L5-M5 -> 164600.6 | O5: =F5*IF(A5="2025",INDEX(Products!$D$2:$D$13,MATCH(D5,Products!$A$2:$A$13,0)),INDEX(Products!$F$2:$F$13,MATCH(D5,Products!$A$2:$A$13,0))) -> 115144 | P5: =N5-O5 -> 49456.601
A6: 2025 | B6: 5 | C6: C001 | D6: HYD-03 | E6: =INDEX(Products!$B$2:$B$13,MATCH(D6,Products!$A$2:$A$13,0)) -> Hydroprocessing | F6: 19.3 | G6: =IF(A6="2025",INDEX(Products!$C$2:$C$13,MATCH(D6,Products!$A$2:$A$13,0)),INDEX(Products!$E$2:$E$13,MATCH(D6,Products!$A$2:$A$13,0))) -> 12450 | H6: =IF(A6="2025",INDEX(Customers!$D$2:$D$41,MATCH(C6,Customers!$A$2:$A$41,0)),INDEX(Customers!$F$2:$F$41,MATCH(C6,Customers!$A$2:$A$41,0))) -> 0.072 | I6: =F6*G6 -> 240285 | J6: =I6*(1-H6) -> 222984.48 | K6: =J6*INDEX(Customers!$G$2:$G$41,MATCH(C6,Customers!$A$2:$A$41,0)) -> 0 | L6: =F6*INDEX(Customers!$H$2:$H$41,MATCH(C6,Customers!$A$2:$A$41,0)) -> 5404 | M6: =J6*INDEX(Customers!$I$2:$I$41,MATCH(C6,Customers!$A$2:$A$41,0))/365*Assumptions!$B$6 -> 2932.3986 | N6: =J6-K6-L6-M6 -> 214648.08 | O6: =F6*IF(A6="2025",INDEX(Products!$D$2:$D$13,MATCH(D6,Products!$A$2:$A$13,0)),INDEX(Products!$F$2:$F$13,MATCH(D6,Products!$A$2:$A$13,0))) -> 150154 | P6: =N6-O6 -> 64494.081
A7: 2025 | B7: 6 | C7: C001 | D7: HYD-03 | E7: =INDEX(Products!$B$2:$B$13,MATCH(D7,Products!$A$2:$A$13,0)) -> Hydroprocessing | F7: 12.7 | G7: =IF(A7="2025",INDEX(Products!$C$2:$C$13,MATCH(D7,Products!$A$2:$A$13,0)),INDEX(Products!$E$2:$E$13,MATCH(D7,Products!$A$2:$A$13,0))) -> 12450 | H7: =IF(A7="2025",INDEX(Customers!$D$2:$D$41,MATCH(C7,Customers!$A$2:$A$41,0)),INDEX(Customers!$F$2:$F$41,MATCH(C7,Customers!$A$2:$A$41,0))) -> 0.072 | I7: =F7*G7 -> 158115 | J7: =I7*(1-H7) -> 146730.72 | K7: =J7*INDEX(Customers!$G$2:$G$41,MATCH(C7,Customers!$A$2:$A$41,0)) -> 0 | L7: =F7*INDEX(Customers!$H$2:$H$41,MATCH(C7,Customers!$A$2:$A$41,0)) -> 3556 | M7: =J7*INDEX(Customers!$I$2:$I$41,MATCH(C7,Customers!$A$2:$A$41,0))/365*Assumptions!$B$6 -> 1929.6095 | N7: =J7-K7-L7-M7 -> 141245.11 | O7: =F7*IF(A7="2025",INDEX(Products!$D$2:$D$13,MATCH(D7,Products!$A$2:$A$13,0)),INDEX(Products!$F$2:$F$13,MATCH(D7,Products!$A$2:$A$13,0))) -> 98806 | P7: =N7-O7 -> 42439.111
A8: 2025 | B8: 7 | C8: C001 | D8: HYD-03 | E8: =INDEX(Products!$B$2:$B$13,MATCH(D8,Products!$A$2:$A$13,0)) -> Hydroprocessing | F8: 17.9 | G8: =IF(A8="2025",INDEX(Products!$C$2:$C$13,MATCH(D8,Products!$A$2:$A$13,0)),INDEX(Products!$E$2:$E$13,MATCH(D8,Products!$A$2:$A$13,0))) -> 12450 | H8: =IF(A8="2025",INDEX(Customers!$D$2:$D$41,MATCH(C8,Customers!$A$2:$A$41,0)),INDEX(Customers!$F$2:$F$41,MATCH(C8,Customers!$A$2:$A$41,0))) -> 0.072 | I8: =F8*G8 -> 222855 | J8: =I8*(1-H8) -> 206809.44 | K8: =J8*INDEX(Customers!$G$2:$G$41,MATCH(C8,Customers!$A$2:$A$41,0)) -> 0 | L8: =F8*INDEX(Customers!$H$2:$H$41,MATCH(C8,Customers!$A$2:$A$41,0)) -> 5012 | M8: =J8*INDEX(Customers!$I$2:$I$41,MATCH(C8,Customers!$A$2:$A$41,0))/365*Assumptions!$B$6 -> 2719.6858 | N8: =J8-K8-L8-M8 -> 199077.75 | O8: =F8*IF(A8="2025",INDEX(Products!$D$2:$D$13,MATCH(D8,Products!$A$2:$A$13,0)),INDEX(Products!$F$2:$F$13,MATCH(D8,Products!$A$2:$A$13,0))) -> 139262 | P8: =N8-O8 -> 59815.754
A9: 2025 | B9: 8 | C9: C001 | D9: HYD-03 | E9: =INDEX(Products!$B$2:$B$13,MATCH(D9,Products!$A$2:$A$13,0)) -> Hydroprocessing | F9: 17.3 | G9: =IF(A9="2025",INDEX(Products!$C$2:$C$13,MATCH(D9,Products!$A$2:$A$13,0)),INDEX(Products!$E$2:$E$13,MATCH(D9,Products!$A$2:$A$13,0))) -> 12450 | H9: =IF(A9="2025",INDEX(Customers!$D$2:$D$41,MATCH(C9,Customers!$A$2:$A$41,0)),INDEX(Customers!$F$2:$F$41,MATCH(C9,Customers!$A$2:$A$41,0))) -> 0.072 | I9: =F9*G9 -> 215385 | J9: =I9*(1-H9) -> 199877.28 | K9: =J9*INDEX(Customers!$G$2:$G$41,MATCH(C9,Customers!$A$2:$A$41,0)) -> 0 | L9: =F9*INDEX(Customers!$H$2:$H$41,MATCH(C9,Customers!$A$2:$A$41,0)) -> 4844 | M9: =J9*INDEX(Customers!$I$2:$I$41,MATCH(C9,Customers!$A$2:$A$41,0))/365*Assumptions!$B$6 -> 2628.5231 | N9: =J9-K9-L9-M9 -> 192404.76 | O9: =F9*IF(A9="2025",INDEX(Products!$D$2:$D$13,MATCH(D9,Products!$A$2:$A$13,0)),INDEX(Products!$F$2:$F$13,MATCH(D9,Products!$A$2:$A$13,0))) -> 134594 | P9: =N9-O9 -> 57810.757
A10: 2025 | B10: 9 | C10: C001 | D10: HYD-03 | E10: =INDEX(Products!$B$2:$B$13,MATCH(D10,Products!$A$2:$A$13,0)) -> Hydroprocessing | F10: 12.8 | G10: =IF(A10="2025",INDEX(Products!$C$2:$C$13,MATCH(D10,Products!$A$2:$A$13,0)),INDEX(Products!$E$2:$E$13,MATCH(D10,Products!$A$2:$A$13,0))) -> 12450 | H10: =IF(A10="2025",INDEX(Customers!$D$2:$D$41,MATCH(C10,Customers!$A$2:$A$41,0)),INDEX(Customers!$F$2:$F$41,MATCH(C10,Customers!$A$2:$A$41,0))) -> 0.072 | I10: =F10*G10 -> 159360 | J10: =I10*(1-H10) -> 147886.08 | K10: =J10*INDEX(Customers!$G$2:$G$41,MATCH(C10,Customers!$A$2:$A$41,0)) -> 0 | L10: =F10*INDEX(Customers!$H$2:$H$41,MATCH(C10,Customers!$A$2:$A$41,0)) -> 3584 | M10: =J10*INDEX(Customers!$I$2:$I$41,MATCH(C10,Customers!$A$2:$A$41,0))/365*Assumptions!$B$6 -> 1944.8032 | N10: =J10-K10-L10-M10 -> 142357.28 | O10: =F10*IF(A10="2025",INDEX(Products!$D$2:$D$13,MATCH(D10,Products!$A$2:$A$13,0)),INDEX(Products!$F$2:$F$13,MATCH(D10,Products!$A$2:$A$13,0))) -> 99584 | P10: =N10-O10 -> 42773.277
A11: 2025 | B11: 10 | C11: C001 | D11: HYD-03 | E11: =INDEX(Products!$B$2:$B$13,MATCH(D11,Products!$A$2:$A$13,0)) -> Hydroprocessing | F11: 16.9 | G11: =IF(A11="2025",INDEX(Products!$C$2:$C$13,MATCH(D11,Products!$A$2:$A$13,0)),INDEX(Products!$E$2:$E$13,MATCH(D11,Products!$A$2:$A$13,0))) -> 12450 | H11: =IF(A11="2025",INDEX(Customers!$D$2:$D$41,MATCH(C11,Customers!$A$2:$A$41,0)),INDEX(Customers!$F$2:$F$41,MATCH(C11,Customers!$A$2:$A$41,0))) -> 0.072 | I11: =F11*G11 -> 210405 | J11: =I11*(1-H11) -> 195255.84 | K11: =J11*INDEX(Customers!$G$2:$G$41,MATCH(C11,Customers!$A$2:$A$41,0)) -> 0 | L11: =F11*INDEX(Customers!$H$2:$H$41,MATCH(C11,Customers!$A$2:$A$41,0)) -> 4732 | M11: =J11*INDEX(Customers!$I$2:$I$41,MATCH(C11,Customers!$A$2:$A$41,0))/365*Assumptions!$B$6 -> 2567.748 | N11: =J11-K11-L11-M11 -> 187956.09 | O11: =F11*IF(A11="2025",INDEX(Products!$D$2:$D$13,MATCH(D11,Products!$A$2:$A$13,0)),INDEX(Products!$F$2:$F$13,MATCH(D11,Products!$A$2:$A$13,0))) -> 131482 | P11: =N11-O11 -> 56474.092
A12: 2025 | B12: 11 | C12: C001 | D12: HYD-03 | E12: =INDEX(Products!$B$2:$B$13,MATCH(D12,Products!$A$2:$A$13,0)) -> Hydroprocessing | F12: 15.6 | G12: =IF(A12="2025",INDEX(Products!$C$2:$C$13,MATCH(D12,Products!$A$2:$A$13,0)),INDEX(Products!$E$2:$E$13,MATCH(D12,Products!$A$2:$A$13,0))) -> 12450 | H12: =IF(A12="2025",INDEX(Customers!$D$2:$D$41,MATCH(C12,Customers!$A$2:$A$41,0)),INDEX(Customers!$F$2:$F$41,MATCH(C12,Customers!$A$2:$A$41,0))) -> 0.072 | I12: =F12*G12 -> 194220 | J12: =I12*(1-H12) -> 180236.16 | K12: =J12*INDEX(Customers!$G$2:$G$41,MATCH(C12,Customers!$A$2:$A$41,0)) -> 0 | L12: =F12*INDEX(Customers!$H$2:$H$41,MATCH(C12,Customers!$A$2:$A$41,0)) -> 4368 | M12: =J12*INDEX(Customers!$I$2:$I$41,MATCH(C12,Customers!$A$2:$A$41,0))/365*Assumptions!$B$6 -> 2370.229 | N12: =J12-K12-L12-M12 -> 173497.93 | O12: =F12*IF(A12="2025",INDEX(Products!$D$2:$D$13,MATCH(D12,Products!$A$2:$A$13,0)),INDEX(Products!$F$2:$F$13,MATCH(D12,Products!$A$2:$A$13,0))) -> 121368 | P12: =N12-O12 -> 52129.931
A13: 2025 | B13: 12 | C13: C001 | D13: HYD-03 | E13: =INDEX(Products!$B$2:$B$13,MATCH(D13,Products!$A$2:$A$13,0)) -> Hydroprocessing | F13: 15 | G13: =IF(A13="2025",INDEX(Products!$C$2:$C$13,MATCH(D13,Products!$A$2:$A$13,0)),INDEX(Products!$E$2:$E$13,MATCH(D13,Products!$A$2:$A$13,0))) -> 12450 | H13: =IF(A13="2025",INDEX(Customers!$D$2:$D$41,MATCH(C13,Customers!$A$2:$A$41,0)),INDEX(Customers!$F$2:$F$41,MATCH(C13,Customers!$A$2:$A$41,0))) -> 0.072 | I13: =F13*G13 -> 186750 | J13: =I13*(1-H13) -> 173304 | K13: =J13*INDEX(Customers!$G$2:$G$41,MATCH(C13,Customers!$A$2:$A$41,0)) -> 0 | L13: =F13*INDEX(Customers!$H$2:$H$41,MATCH(C13,Customers!$A$2:$A$41,0)) -> 4200 | M13: =J13*INDEX(Customers!$I$2:$I$41,MATCH(C13,Customers!$A$2:$A$41,0))/365*Assumptions!$B$6 -> 2279.0663 | N13: =J13-K13-L13-M13 -> 166824.93 | O13: =F13*IF(A13="2025",INDEX(Products!$D$2:$D$13,MATCH(D13,Products!$A$2:$A$13,0)),INDEX(Products!$F$2:$F$13,MATCH(D13,Products!$A$2:$A$13,0))) -> 116700 | P13: =N13-O13 -> 50124.934
... A2881: 2026 | B2881: 12 | C2881: C040 | D2881: HYD-03 | E2881: =INDEX(Products!$B$2:$B$13,MATCH(D2881,Products!$A$2:$A$13,0)) -> Hydroprocessing | F2881: 6.6 | G2881: =IF(A2881="2025",INDEX(Products!$C$2:$C$13,MATCH(D2881,Products!$A$2:$A$13,0)),INDEX(Products!$E$2:$E$13,MATCH(D2881,Products!$A$2:$A$13,0))) -> 13072.5 | H2881: =IF(A2881="2025",INDEX(Customers!$D$2:$D$41,MATCH(C2881,Customers!$A$2:$A$41,0)),INDEX(Customers!$F$2:$F$41,MATCH(C2881,Customers!$A$2:$A$41,0))) -> 0.069 | I2881: =F2881*G2881 -> 86278.5 | J2881: =I2881*(1-H2881) -> 80325.284 | K2881: =J2881*INDEX(Customers!$G$2:$G$41,MATCH(C2881,Customers!$A$2:$A$41,0)) -> 2409.7585 | L2881: =F2881*INDEX(Customers!$H$2:$H$41,MATCH(C2881,Customers!$A$2:$A$41,0)) -> 726 | M2881: =J2881*INDEX(Customers!$I$2:$I$41,MATCH(C2881,Customers!$A$2:$A$41,0))/365*Assumptions!$B$6 -> 1584.4987 | N2881: =J2881-K2881-L2881-M2881 -> 75605.026 | O2881: =F2881*IF(A2881="2025",INDEX(Products!$D$2:$D$13,MATCH(D2881,Products!$A$2:$A$13,0)),INDEX(Products!$F$2:$F$13,MATCH(D2881,Products!$A$2:$A$13,0))) -> 52888.44 | P2881: =N2881-O2881 -> 22716.586

Sheet Price Waterfall
A1: Pocket Price Waterfall ($/ton, all customers)
A3: Step | B3: FY2025 ($/t) | C3: FY2026 ($/t) | D3: FY2026 % of List
A4: List price | B4: =SUMIFS(Transactions!$I$2:$I$2881,Transactions!$A$2:$A$2881,"2025")/SUMIFS(Transactions!$F$2:$F$2881,Transactions!$A$2:$A$2881,"2025") -> 9689.275 | C4: =SUMIFS(Transactions!$I$2:$I$2881,Transactions!$A$2:$A$2881,"2026")/SUMIFS(Transactions!$F$2:$F$2881,Transactions!$A$2:$A$2881,"2026") -> 10659.096 | D4: =C4/$C$4 -> 1
A5: On-invoice discount | B5: =-(SUMIFS(Transactions!$I$2:$I$2881,Transactions!$A$2:$A$2881,"2025")-SUMIFS(Transactions!$J$2:$J$2881,Transactions!$A$2:$A$2881,"2025"))/SUMIFS(Transactions!$F$2:$F$2881,Transactions!$A$2:$A$2881,"2025") -> -846.67412 | C5: =-(SUMIFS(Transactions!$I$2:$I$2881,Transactions!$A$2:$A$2881,"2026")-SUMIFS(Transactions!$J$2:$J$2881,Transactions!$A$2:$A$2881,"2026"))/SUMIFS(Transactions!$F$2:$F$2881,Transactions!$A$2:$A$2881,"2026") -> -1042.0542 | D5: =C5/$C$4 -> -0.097761969
A6: Invoice price | B6: =SUMIFS(Transactions!$J$2:$J$2881,Transactions!$A$2:$A$2881,"2025")/SUMIFS(Transactions!$F$2:$F$2881,Transactions!$A$2:$A$2881,"2025") -> 8842.6009 | C6: =SUMIFS(Transactions!$J$2:$J$2881,Transactions!$A$2:$A$2881,"2026")/SUMIFS(Transactions!$F$2:$F$2881,Transactions!$A$2:$A$2881,"2026") -> 9617.0414 | D6: =C6/$C$4 -> 0.90223803
A7: Volume rebates | B7: =-SUMIFS(Transactions!$K$2:$K$2881,Transactions!$A$2:$A$2881,"2025")/SUMIFS(Transactions!$F$2:$F$2881,Transactions!$A$2:$A$2881,"2025") -> -134.96179 | C7: =-SUMIFS(Transactions!$K$2:$K$2881,Transactions!$A$2:$A$2881,"2026")/SUMIFS(Transactions!$F$2:$F$2881,Transactions!$A$2:$A$2881,"2026") -> -146.66078 | D7: =C7/$C$4 -> -0.013759215
A8: Freight | B8: =-SUMIFS(Transactions!$L$2:$L$2881,Transactions!$A$2:$A$2881,"2025")/SUMIFS(Transactions!$F$2:$F$2881,Transactions!$A$2:$A$2881,"2025") -> -277.89828 | C8: =-SUMIFS(Transactions!$L$2:$L$2881,Transactions!$A$2:$A$2881,"2026")/SUMIFS(Transactions!$F$2:$F$2881,Transactions!$A$2:$A$2881,"2026") -> -276.19444 | D8: =C8/$C$4 -> -0.025911621
A9: Payment-terms cost | B9: =-SUMIFS(Transactions!$M$2:$M$2881,Transactions!$A$2:$A$2881,"2025")/SUMIFS(Transactions!$F$2:$F$2881,Transactions!$A$2:$A$2881,"2025") -> -111.787 | C9: =-SUMIFS(Transactions!$M$2:$M$2881,Transactions!$A$2:$A$2881,"2026")/SUMIFS(Transactions!$F$2:$F$2881,Transactions!$A$2:$A$2881,"2026") -> -120.57492 | D9: =C9/$C$4 -> -0.011311928
A10: Pocket price | B10: =SUMIFS(Transactions!$N$2:$N$2881,Transactions!$A$2:$A$2881,"2025")/SUMIFS(Transactions!$F$2:$F$2881,Transactions!$A$2:$A$2881,"2025") -> 8317.9538 | C10: =SUMIFS(Transactions!$N$2:$N$2881,Transactions!$A$2:$A$2881,"2026")/SUMIFS(Transactions!$F$2:$F$2881,Transactions!$A$2:$A$2881,"2026") -> 9073.6113 | D10: =C10/$C$4 -> 0.85125527
A12: Price leakage, list to pocket | B12: =1-B10/B4 -> 0.1415298 | C12: =1-C10/C4 -> 0.14874473
A14: Price Realization (FY2026 vs FY2025)
A15: Measure | B15: Change
A16: Announced list increase | B16: =Assumptions!B4 -> 0.05
A17: Realized invoice price change (same-mix basis) | B17: =SUMPRODUCT('PVM Bridge'!D4:D15,'PVM Bridge'!N4:N15)/SUMPRODUCT('PVM Bridge'!D4:D15,'PVM Bridge'!M4:M15)-1 -> 0.037376128
A18: Realized pocket price change (same-mix basis) | B18: ='PVM Bridge'!H16/'PVM Bridge'!I16-1 -> 0.039066398
A19: Realization rate (pocket change / announced) | B19: =B18/B16 -> 0.78132795

Sheet PVM Bridge
A1: Price-Volume-Mix Bridge: Pocket Revenue FY2025 to FY2026, by product
A3: Product | B3: Family | C3: Tons FY25 | D3: Tons FY26 | E3: Pocket $/t FY25 | F3: Pocket $/t FY26 | G3: Pocket Rev FY25 | H3: Pocket Rev FY26 | I3: FY26 Tons at FY25 Price | J3: Price Effect | K3: Pocket Margin FY25 | L3: Pocket Margin FY26 | M3: Invoice $/t FY25 | N3: Invoice $/t FY26
A4: FCC-01 | B4: FCC | C4: =SUMIFS(Transactions!$F$2:$F$2881,Transactions!$D$2:$D$2881,$A4,Transactions!$A$2:$A$2881,"2025") -> 2504.7 | D4: =SUMIFS(Transactions!$F$2:$F$2881,Transactions!$D$2:$D$2881,$A4,Transactions!$A$2:$A$2881,"2026") -> 2348.6 | E4: =IFERROR(G4/C4,0) -> 2685.7399 | F4: =IFERROR(H4/D4,0) -> 2800.8592 | G4: =SUMIFS(Transactions!$N$2:$N$2881,Transactions!$D$2:$D$2881,$A4,Transactions!$A$2:$A$2881,"2025") -> 6726972.8 | H4: =SUMIFS(Transactions!$N$2:$N$2881,Transactions!$D$2:$D$2881,$A4,Transactions!$A$2:$A$2881,"2026") -> 6578097.9 | I4: =D4*E4 -> 6307728.8 | J4: =D4*(F4-E4) -> 270369.12 | K4: =SUMIFS(Transactions!$P$2:$P$2881,Transactions!$D$2:$D$2881,$A4,Transactions!$A$2:$A$2881,"2025") -> 1241679.8 | L4: =SUMIFS(Transactions!$P$2:$P$2881,Transactions!$D$2:$D$2881,$A4,Transactions!$A$2:$A$2881,"2026") -> 1280360.9 | M4: =IFERROR(SUMIFS(Transactions!$J$2:$J$2881,Transactions!$D$2:$D$2881,$A4,Transactions!$A$2:$A$2881,"2025")/C4,0) -> 3012.1972 | N4: =IFERROR(SUMIFS(Transactions!$J$2:$J$2881,Transactions!$D$2:$D$2881,$A4,Transactions!$A$2:$A$2881,"2026")/D4,0) -> 3128.1789
A5: FCC-02 | B5: FCC | C5: =SUMIFS(Transactions!$F$2:$F$2881,Transactions!$D$2:$D$2881,$A5,Transactions!$A$2:$A$2881,"2025") -> 2992.7 | D5: =SUMIFS(Transactions!$F$2:$F$2881,Transactions!$D$2:$D$2881,$A5,Transactions!$A$2:$A$2881,"2026") -> 2760.6 | E5: =IFERROR(G5/C5,0) -> 3033.3628 | F5: =IFERROR(H5/D5,0) -> 3155.2236 | G5: =SUMIFS(Transactions!$N$2:$N$2881,Transactions!$D$2:$D$2881,$A5,Transactions!$A$2:$A$2881,"2025") -> 9077945 | H5: =SUMIFS(Transactions!$N$2:$N$2881,Transactions!$D$2:$D$2881,$A5,Transactions!$A$2:$A$2881,"2026") -> 8710310.2 | I5: =D5*E5 -> 8373901.5 | J5: =D5*(F5-E5) -> 336408.71 | K5: =SUMIFS(Transactions!$P$2:$P$2881,Transactions!$D$2:$D$2881,$A5,Transactions!$A$2:$A$2881,"2025") -> 1895465 | L5: =SUMIFS(Transactions!$P$2:$P$2881,Transactions!$D$2:$D$2881,$A5,Transactions!$A$2:$A$2881,"2026") -> 1886107 | M5: =IFERROR(SUMIFS(Transactions!$J$2:$J$2881,Transactions!$D$2:$D$2881,$A5,Transactions!$A$2:$A$2881,"2025")/C5,0) -> 3398.9305 | N5: =IFERROR(SUMIFS(Transactions!$J$2:$J$2881,Transactions!$D$2:$D$2881,$A5,Transactions!$A$2:$A$2881,"2026")/D5,0) -> 3521.5895
A6: FCC-03 | B6: FCC | C6: =SUMIFS(Transactions!$F$2:$F$2881,Transactions!$D$2:$D$2881,$A6,Transactions!$A$2:$A$2881,"2025") -> 2591.7 | D6: =SUMIFS(Transactions!$F$2:$F$2881,Transactions!$D$2:$D$2881,$A6,Transactions!$A$2:$A$2881,"2026") -> 2456.7 | E6: =IFERROR(G6/C6,0) -> 2929.8798 | F6: =IFERROR(H6/D6,0) -> 3054.6413 | G6: =SUMIFS(Transactions!$N$2:$N$2881,Transactions!$D$2:$D$2881,$A6,Transactions!$A$2:$A$2881,"2025") -> 7593369.4 | H6: =SUMIFS(Transactions!$N$2:$N$2881,Transactions!$D$2:$D$2881,$A6,Transactions!$A$2:$A$2881,"2026") -> 7504337.3 | I6: =D6*E6 -> 7197835.6 | J6: =D6*(F6-E6) -> 306501.66 | K6: =SUMIFS(Transactions!$P$2:$P$2881,Transactions!$D$2:$D$2881,$A6,Transactions!$A$2:$A$2881,"2025") -> 1347372.4 | L6: =SUMIFS(Transactions!$P$2:$P$2881,Transactions!$D$2:$D$2881,$A6,Transactions!$A$2:$A$2881,"2026") -> 1406070.8 | M6: =IFERROR(SUMIFS(Transactions!$J$2:$J$2881,Transactions!$D$2:$D$2881,$A6,Transactions!$A$2:$A$2881,"2025")/C6,0) -> 3277.5314 | N6: =IFERROR(SUMIFS(Transactions!$J$2:$J$2881,Transactions!$D$2:$D$2881,$A6,Transactions!$A$2:$A$2881,"2026")/D6,0) -> 3408.1623
A7: FCC-04 | B7: FCC | C7: =SUMIFS(Transactions!$F$2:$F$2881,Transactions!$D$2:$D$2881,$A7,Transactions!$A$2:$A$2881,"2025") -> 1886.8 | D7: =SUMIFS(Transactions!$F$2:$F$2881,Transactions!$D$2:$D$2881,$A7,Transactions!$A$2:$A$2881,"2026") -> 1797 | E7: =IFERROR(G7/C7,0) -> 3469.7344 | F7: =IFERROR(H7/D7,0) -> 3628.8517 | G7: =SUMIFS(Transactions!$N$2:$N$2881,Transactions!$D$2:$D$2881,$A7,Transactions!$A$2:$A$2881,"2025") -> 6546694.8 | H7: =SUMIFS(Transactions!$N$2:$N$2881,Transactions!$D$2:$D$2881,$A7,Transactions!$A$2:$A$2881,"2026") -> 6521046.5 | I7: =D7*E7 -> 6235112.7 | J7: =D7*(F7-E7) -> 285933.83 | K7: =SUMIFS(Transactions!$P$2:$P$2881,Transactions!$D$2:$D$2881,$A7,Transactions!$A$2:$A$2881,"2025") -> 1320258.8 | L7: =SUMIFS(Transactions!$P$2:$P$2881,Transactions!$D$2:$D$2881,$A7,Transactions!$A$2:$A$2881,"2026") -> 1394025.8 | M7: =IFERROR(SUMIFS(Transactions!$J$2:$J$2881,Transactions!$D$2:$D$2881,$A7,Transactions!$A$2:$A$2881,"2025")/C7,0) -> 3919.2532 | N7: =IFERROR(SUMIFS(Transactions!$J$2:$J$2881,Transactions!$D$2:$D$2881,$A7,Transactions!$A$2:$A$2881,"2026")/D7,0) -> 4081.664
A8: HYD-01 | B8: Hydroprocessing | C8: =SUMIFS(Transactions!$F$2:$F$2881,Transactions!$D$2:$D$2881,$A8,Transactions!$A$2:$A$2881,"2025") -> 532 | D8: =SUMIFS(Transactions!$F$2:$F$2881,Transactions!$D$2:$D$2881,$A8,Transactions!$A$2:$A$2881,"2026") -> 538.7 | E8: =IFERROR(G8/C8,0) -> 11217.832 | F8: =IFERROR(H8/D8,0) -> 11685.654 | G8: =SUMIFS(Transactions!$N$2:$N$2881,Transactions!$D$2:$D$2881,$A8,Transactions!$A$2:$A$2881,"2025") -> 5967886.4 | H8: =SUMIFS(Transactions!$N$2:$N$2881,Transactions!$D$2:$D$2881,$A8,Transactions!$A$2:$A$2881,"2026") -> 6295061.9 | I8: =D8*E8 -> 6043045.9 | J8: =D8*(F8-E8) -> 252015.99 | K8: =SUMIFS(Transactions!$P$2:$P$2881,Transactions!$D$2:$D$2881,$A8,Transactions!$A$2:$A$2881,"2025") -> 2089606.4 | L8: =SUMIFS(Transactions!$P$2:$P$2881,Transactions!$D$2:$D$2881,$A8,Transactions!$A$2:$A$2881,"2026") -> 2250125.2 | M8: =IFERROR(SUMIFS(Transactions!$J$2:$J$2881,Transactions!$D$2:$D$2881,$A8,Transactions!$A$2:$A$2881,"2025")/C8,0) -> 11845.002 | N8: =IFERROR(SUMIFS(Transactions!$J$2:$J$2881,Transactions!$D$2:$D$2881,$A8,Transactions!$A$2:$A$2881,"2026")/D8,0) -> 12322.962
A9: HYD-02 | B9: Hydroprocessing | C9: =SUMIFS(Transactions!$F$2:$F$2881,Transactions!$D$2:$D$2881,$A9,Transactions!$A$2:$A$2881,"2025") -> 1127.4 | D9: =SUMIFS(Transactions!$F$2:$F$2881,Transactions!$D$2:$D$2881,$A9,Transactions!$A$2:$A$2881,"2026") -> 1013.4 | E9: =IFERROR(G9/C9,0) -> 12533.915 | F9: =IFERROR(H9/D9,0) -> 13087.905 | G9: =SUMIFS(Transactions!$N$2:$N$2881,Transactions!$D$2:$D$2881,$A9,Transactions!$A$2:$A$2881,"2025") -> 14130736 | H9: =SUMIFS(Transactions!$N$2:$N$2881,Transactions!$D$2:$D$2881,$A9,Transactions!$A$2:$A$2881,"2026") -> 13263283 | I9: =D9*E9 -> 12701870 | J9: =D9*(F9-E9) -> 561412.79 | K9: =SUMIFS(Transactions!$P$2:$P$2881,Transactions!$D$2:$D$2881,$A9,Transactions!$A$2:$A$2881,"2025") -> 3442984.1 | L9: =SUMIFS(Transactions!$P$2:$P$2881,Transactions!$D$2:$D$2881,$A9,Transactions!$A$2:$A$2881,"2026") -> 3368039.6 | M9: =IFERROR(SUMIFS(Transactions!$J$2:$J$2881,Transactions!$D$2:$D$2881,$A9,Transactions!$A$2:$A$2881,"2025")/C9,0) -> 13153.294 | N9: =IFERROR(SUMIFS(Transactions!$J$2:$J$2881,Transactions!$D$2:$D$2881,$A9,Transactions!$A$2:$A$2881,"2026")/D9,0) -> 13706.576
A10: HYD-03 | B10: Hydroprocessing | C10: =SUMIFS(Transactions!$F$2:$F$2881,Transactions!$D$2:$D$2881,$A10,Transactions!$A$2:$A$2881,"2025") -> 1610.6 | D10: =SUMIFS(Transactions!$F$2:$F$2881,Transactions!$D$2:$D$2881,$A10,Transactions!$A$2:$A$2881,"2026") -> 1529.5 | E10: =IFERROR(G10/C10,0) -> 10512.562 | F10: =IFERROR(H10/D10,0) -> 10909.205 | G10: =SUMIFS(Transactions!$N$2:$N$2881,Transactions!$D$2:$D$2881,$A10,Transactions!$A$2:$A$2881,"2025") -> 16931533 | H10: =SUMIFS(Transactions!$N$2:$N$2881,Transactions!$D$2:$D$2881,$A10,Transactions!$A$2:$A$2881,"2026") -> 16685629 | I10: =D10*E10 -> 16078964 | J10: =D10*(F10-E10) -> 606665.54 | K10: =SUMIFS(Transactions!$P$2:$P$2881,Transactions!$D$2:$D$2881,$A10,Transactions!$A$2:$A$2881,"2025") -> 4401064.8 | L10: =SUMIFS(Transactions!$P$2:$P$2881,Transactions!$D$2:$D$2881,$A10,Transactions!$A$2:$A$2881,"2026") -> 4429134.2 | M10: =IFERROR(SUMIFS(Transactions!$J$2:$J$2881,Transactions!$D$2:$D$2881,$A10,Transactions!$A$2:$A$2881,"2025")/C10,0) -> 11125.772 | N10: =IFERROR(SUMIFS(Transactions!$J$2:$J$2881,Transactions!$D$2:$D$2881,$A10,Transactions!$A$2:$A$2881,"2026")/D10,0) -> 11526.558
A11: HYD-04 | B11: Hydroprocessing | C11: =SUMIFS(Transactions!$F$2:$F$2881,Transactions!$D$2:$D$2881,$A11,Transactions!$A$2:$A$2881,"2025") -> 855 | D11: =SUMIFS(Transactions!$F$2:$F$2881,Transactions!$D$2:$D$2881,$A11,Transactions!$A$2:$A$2881,"2026") -> 836.8 | E11: =IFERROR(G11/C11,0) -> 10220.809 | F11: =IFERROR(H11/D11,0) -> 10577.582 | G11: =SUMIFS(Transactions!$N$2:$N$2881,Transactions!$D$2:$D$2881,$A11,Transactions!$A$2:$A$2881,"2025") -> 8738791.5 | H11: =SUMIFS(Transactions!$N$2:$N$2881,Transactions!$D$2:$D$2881,$A11,Transactions!$A$2:$A$2881,"2026") -> 8851320.6 | I11: =D11*E11 -> 8552772.8 | J11: =D11*(F11-E11) -> 298547.85 | K11: =SUMIFS(Transactions!$P$2:$P$2881,Transactions!$D$2:$D$2881,$A11,Transactions!$A$2:$A$2881,"2025") -> 2463091.5 | L11: =SUMIFS(Transactions!$P$2:$P$2881,Transactions!$D$2:$D$2881,$A11,Transactions!$A$2:$A$2881,"2026") -> 2524945.2 | M11: =IFERROR(SUMIFS(Transactions!$J$2:$J$2881,Transactions!$D$2:$D$2881,$A11,Transactions!$A$2:$A$2881,"2025")/C11,0) -> 10628.074 | N11: =IFERROR(SUMIFS(Transactions!$J$2:$J$2881,Transactions!$D$2:$D$2881,$A11,Transactions!$A$2:$A$2881,"2026")/D11,0) -> 10989.954
A12: SPE-01 | B12: Specialty | C12: =SUMIFS(Transactions!$F$2:$F$2881,Transactions!$D$2:$D$2881,$A12,Transactions!$A$2:$A$2881,"2025") -> 398.7 | D12: =SUMIFS(Transactions!$F$2:$F$2881,Transactions!$D$2:$D$2881,$A12,Transactions!$A$2:$A$2881,"2026") -> 413.2 | E12: =IFERROR(G12/C12,0) -> 26362.941 | F12: =IFERROR(H12/D12,0) -> 27227.664 | G12: =SUMIFS(Transactions!$N$2:$N$2881,Transactions!$D$2:$D$2881,$A12,Transactions!$A$2:$A$2881,"2025") -> 10510905 | H12: =SUMIFS(Transactions!$N$2:$N$2881,Transactions!$D$2:$D$2881,$A12,Transactions!$A$2:$A$2881,"2026") -> 11250471 | I12: =D12*E12 -> 10893167 | J12: =D12*(F12-E12) -> 357303.47 | K12: =SUMIFS(Transactions!$P$2:$P$2881,Transactions!$D$2:$D$2881,$A12,Transactions!$A$2:$A$2881,"2025") -> 4805507.5 | L12: =SUMIFS(Transactions!$P$2:$P$2881,Transactions!$D$2:$D$2881,$A12,Transactions!$A$2:$A$2881,"2026") -> 5160191.9 | M12: =IFERROR(SUMIFS(Transactions!$J$2:$J$2881,Transactions!$D$2:$D$2881,$A12,Transactions!$A$2:$A$2881,"2025")/C12,0) -> 27224.229 | N12: =IFERROR(SUMIFS(Transactions!$J$2:$J$2881,Transactions!$D$2:$D$2881,$A12,Transactions!$A$2:$A$2881,"2026")/D12,0) -> 28117.714
A13: SPE-02 | B13: Specialty | C13: =SUMIFS(Transactions!$F$2:$F$2881,Transactions!$D$2:$D$2881,$A13,Transactions!$A$2:$A$2881,"2025") -> 576 | D13: =SUMIFS(Transactions!$F$2:$F$2881,Transactions!$D$2:$D$2881,$A13,Transactions!$A$2:$A$2881,"2026") -> 641.7 | E13: =IFERROR(G13/C13,0) -> 22513.435 | F13: =IFERROR(H13/D13,0) -> 23377.816 | G13: =SUMIFS(Transactions!$N$2:$N$2881,Transactions!$D$2:$D$2881,$A13,Transactions!$A$2:$A$2881,"2025") -> 12967739 | H13: =SUMIFS(Transactions!$N$2:$N$2881,Transactions!$D$2:$D$2881,$A13,Transactions!$A$2:$A$2881,"2026") -> 15001545 | I13: =D13*E13 -> 14446872 | J13: =D13*(F13-E13) -> 554673.22 | K13: =SUMIFS(Transactions!$P$2:$P$2881,Transactions!$D$2:$D$2881,$A13,Transactions!$A$2:$A$2881,"2025") -> 5911738.8 | L13: =SUMIFS(Transactions!$P$2:$P$2881,Transactions!$D$2:$D$2881,$A13,Transactions!$A$2:$A$2881,"2026") -> 6904895 | M13: =IFERROR(SUMIFS(Transactions!$J$2:$J$2881,Transactions!$D$2:$D$2881,$A13,Transactions!$A$2:$A$2881,"2025")/C13,0) -> 23332.197 | N13: =IFERROR(SUMIFS(Transactions!$J$2:$J$2881,Transactions!$D$2:$D$2881,$A13,Transactions!$A$2:$A$2881,"2026")/D13,0) -> 24210.126
A14: SPE-03 | B14: Specialty | C14: =SUMIFS(Transactions!$F$2:$F$2881,Transactions!$D$2:$D$2881,$A14,Transactions!$A$2:$A$2881,"2025") -> 680.5 | D14: =SUMIFS(Transactions!$F$2:$F$2881,Transactions!$D$2:$D$2881,$A14,Transactions!$A$2:$A$2881,"2026") -> 710.2 | E14: =IFERROR(G14/C14,0) -> 26095.657 | F14: =IFERROR(H14/D14,0) -> 27116.618 | G14: =SUMIFS(Transactions!$N$2:$N$2881,Transactions!$D$2:$D$2881,$A14,Transactions!$A$2:$A$2881,"2025") -> 17758095 | H14: =SUMIFS(Transactions!$N$2:$N$2881,Transactions!$D$2:$D$2881,$A14,Transactions!$A$2:$A$2881,"2026") -> 19258222 | I14: =D14*E14 -> 18533136 | J14: =D14*(F14-E14) -> 725086.54 | K14: =SUMIFS(Transactions!$P$2:$P$2881,Transactions!$D$2:$D$2881,$A14,Transactions!$A$2:$A$2881,"2025") -> 7251174.8 | L14: =SUMIFS(Transactions!$P$2:$P$2881,Transactions!$D$2:$D$2881,$A14,Transactions!$A$2:$A$2881,"2026") -> 7963769.7 | M14: =IFERROR(SUMIFS(Transactions!$J$2:$J$2881,Transactions!$D$2:$D$2881,$A14,Transactions!$A$2:$A$2881,"2025")/C14,0) -> 27440.723 | N14: =IFERROR(SUMIFS(Transactions!$J$2:$J$2881,Transactions!$D$2:$D$2881,$A14,Transactions!$A$2:$A$2881,"2026")/D14,0) -> 28489.634
A15: SPE-04 | B15: Specialty | C15: =SUMIFS(Transactions!$F$2:$F$2881,Transactions!$D$2:$D$2881,$A15,Transactions!$A$2:$A$2881,"2025") -> 664.7 | D15: =SUMIFS(Transactions!$F$2:$F$2881,Transactions!$D$2:$D$2881,$A15,Transactions!$A$2:$A$2881,"2026") -> 770.2 | E15: =IFERROR(G15/C15,0) -> 29542.334 | F15: =IFERROR(H15/D15,0) -> 30634.064 | G15: =SUMIFS(Transactions!$N$2:$N$2881,Transactions!$D$2:$D$2881,$A15,Transactions!$A$2:$A$2881,"2025") -> 19636789 | H15: =SUMIFS(Transactions!$N$2:$N$2881,Transactions!$D$2:$D$2881,$A15,Transactions!$A$2:$A$2881,"2026") -> 23594356 | I15: =D15*E15 -> 22753506 | J15: =D15*(F15-E15) -> 840850.49 | K15: =SUMIFS(Transactions!$P$2:$P$2881,Transactions!$D$2:$D$2881,$A15,Transactions!$A$2:$A$2881,"2025") -> 9652995.3 | L15: =SUMIFS(Transactions!$P$2:$P$2881,Transactions!$D$2:$D$2881,$A15,Transactions!$A$2:$A$2881,"2026") -> 11678900 | M15: =IFERROR(SUMIFS(Transactions!$J$2:$J$2881,Transactions!$D$2:$D$2881,$A15,Transactions!$A$2:$A$2881,"2025")/C15,0) -> 30830.349 | N15: =IFERROR(SUMIFS(Transactions!$J$2:$J$2881,Transactions!$D$2:$D$2881,$A15,Transactions!$A$2:$A$2881,"2026")/D15,0) -> 31927.643
A16: Total | C16: =SUM(C4:C15) -> 16420.8 | D16: =SUM(D4:D15) -> 15816.6 | G16: =SUM(G4:G15) -> 1.3658746e+08 | H16: =SUM(H4:H15) -> 1.4351368e+08 | I16: =SUM(I4:I15) -> 1.3811791e+08 | J16: =SUM(J4:J15) -> 5395769.2 | K16: =SUM(K4:K15) -> 45822939 | L16: =SUM(L4:L15) -> 50246565
A18: Bridge
A19: Component | B19: Pocket Revenue ($) | C19: % of FY25
A20: FY2025 pocket revenue | B20: =G16 -> 1.3658746e+08 | C20: =B20/$B$20 -> 1
A21: Volume effect | B21: =(D16-C16)*(G16/C16) -> -5025707.7 | C21: =B21/$B$20 -> -0.036794797
A22: Mix effect | B22: =I16-D16*(G16/C16) -> 6556162.5 | C22: =B22/$B$20 -> 0.047999741
A23: Price effect | B23: =J16 -> 5395769.2 | C23: =B23/$B$20 -> 0.039504134
A24: FY2026 pocket revenue | B24: =SUM(B20:B23) -> 1.4351368e+08 | C24: =B24/$B$20 -> 1.0507091
A25: Check vs actual FY2026 (should be 0) | B25: =B24-H16 -> 0 | C25: =B25/$B$20 -> 0
A27: Pocket margin % FY25 / FY26 | B27: =K16/G16 -> 0.33548424 | C27: =L16/H16 -> 0.3501169

Sheet Customer Profitability
A1: Customer Profitability FY2026 (pocket margin less cost-to-serve)
A3: Customer | B3: Segment | C3: Tier | D3: Pocket Revenue ($) | E3: Pocket Margin ($) | F3: Cost-to-Serve ($) | G3: Customer Net Profit ($) | H3: Net Margin % | I3: Rank | J3: Cumulative Profit % (whale curve) | K3: Price Uplift to Target Margin
A4: C023 | B4: =INDEX(Customers!$B$2:$B$41,MATCH(A4,Customers!$A$2:$A$41,0)) -> Petrochemical | C4: =INDEX(Customers!$C$2:$C$41,MATCH(A4,Customers!$A$2:$A$41,0)) -> Core | D4: =SUMIFS(Transactions!$N$2:$N$2881,Transactions!$C$2:$C$2881,$A4,Transactions!$A$2:$A$2881,"2026") -> 8770628.3 | E4: =SUMIFS(Transactions!$P$2:$P$2881,Transactions!$C$2:$C$2881,$A4,Transactions!$A$2:$A$2881,"2026") -> 3517243.1 | F4: =INDEX(Customers!$J$2:$J$41,MATCH(A4,Customers!$A$2:$A$41,0)) -> 513000 | G4: =E4-F4 -> 3004243.1 | H4: =IFERROR(G4/D4,0) -> 0.34253454 | I4: =RANK(G4,$G$4:$G$43) -> 1 | J4: =SUM($G$4:G4)/SUM($G$4:$G$43) -> 0.091540965 | K4: =MAX(0,(Assumptions!$B$7*D4-G4)/(1-Assumptions!$B$7))/D4 -> 0
A5: C001 | B5: =INDEX(Customers!$B$2:$B$41,MATCH(A5,Customers!$A$2:$A$41,0)) -> Refining | C5: =INDEX(Customers!$C$2:$C$41,MATCH(A5,Customers!$A$2:$A$41,0)) -> Core | D5: =SUMIFS(Transactions!$N$2:$N$2881,Transactions!$C$2:$C$2881,$A5,Transactions!$A$2:$A$2881,"2026") -> 7946978.8 | E5: =SUMIFS(Transactions!$P$2:$P$2881,Transactions!$C$2:$C$2881,$A5,Transactions!$A$2:$A$2881,"2026") -> 2804021.9 | F5: =INDEX(Customers!$J$2:$J$41,MATCH(A5,Customers!$A$2:$A$41,0)) -> 420000 | G5: =E5-F5 -> 2384021.9 | H5: =IFERROR(G5/D5,0) -> 0.29999098 | I5: =RANK(G5,$G$4:$G$43) -> 2 | J5: =SUM($G$4:G5)/SUM($G$4:$G$43) -> 0.16418344 | K5: =MAX(0,(Assumptions!$B$7*D5-G5)/(1-Assumptions!$B$7))/D5 -> 0
A6: C004 | B6: =INDEX(Customers!$B$2:$B$41,MATCH(A6,Customers!$A$2:$A$41,0)) -> Refining | C6: =INDEX(Customers!$C$2:$C$41,MATCH(A6,Customers!$A$2:$A$41,0)) -> Core | D6: =SUMIFS(Transactions!$N$2:$N$2881,Transactions!$C$2:$C$2881,$A6,Transactions!$A$2:$A$2881,"2026") -> 7474309.1 | E6: =SUMIFS(Transactions!$P$2:$P$2881,Transactions!$C$2:$C$2881,$A6,Transactions!$A$2:$A$2881,"2026") -> 2681937.5 | F6: =INDEX(Customers!$J$2:$J$41,MATCH(A6,Customers!$A$2:$A$41,0)) -> 301000 | G6: =E6-F6 -> 2380937.5 | H6: =IFERROR(G6/D6,0) -> 0.31854951 | I6: =RANK(G6,$G$4:$G$43) -> 3 | J6: =SUM($G$4:G6)/SUM($G$4:$G$43) -> 0.23673194 | K6: =MAX(0,(Assumptions!$B$7*D6-G6)/(1-Assumptions!$B$7))/D6 -> 0
A7: C034 | B7: =INDEX(Customers!$B$2:$B$41,MATCH(A7,Customers!$A$2:$A$41,0)) -> Refining | C7: =INDEX(Customers!$C$2:$C$41,MATCH(A7,Customers!$A$2:$A$41,0)) -> Strategic | D7: =SUMIFS(Transactions!$N$2:$N$2881,Transactions!$C$2:$C$2881,$A7,Transactions!$A$2:$A$2881,"2026") -> 12678964 | E7: =SUMIFS(Transactions!$P$2:$P$2881,Transactions!$C$2:$C$2881,$A7,Transactions!$A$2:$A$2881,"2026") -> 3092264.1 | F7: =INDEX(Customers!$J$2:$J$41,MATCH(A7,Customers!$A$2:$A$41,0)) -> 835000 | G7: =E7-F7 -> 2257264.1 | H7: =IFERROR(G7/D7,0) -> 0.17803221 | I7: =RANK(G7,$G$4:$G$43) -> 4 | J7: =SUM($G$4:G7)/SUM($G$4:$G$43) -> 0.30551203 | K7: =MAX(0,(Assumptions!$B$7*D7-G7)/(1-Assumptions!$B$7))/D7 -> 0.095957049
A8: C018 | B8: =INDEX(Customers!$B$2:$B$41,MATCH(A8,Customers!$A$2:$A$41,0)) -> Specialty Chemicals | C8: =INDEX(Customers!$C$2:$C$41,MATCH(A8,Customers!$A$2:$A$41,0)) -> Core | D8: =SUMIFS(Transactions!$N$2:$N$2881,Transactions!$C$2:$C$2881,$A8,Transactions!$A$2:$A$2881,"2026") -> 6543390.5 | E8: =SUMIFS(Transactions!$P$2:$P$2881,Transactions!$C$2:$C$2881,$A8,Transactions!$A$2:$A$2881,"2026") -> 2825228.5 | F8: =INDEX(Customers!$J$2:$J$41,MATCH(A8,Customers!$A$2:$A$41,0)) -> 641000 | G8: =E8-F8 -> 2184228.5 | H8: =IFERROR(G8/D8,0) -> 0.33380684 | I8: =RANK(G8,$G$4:$G$43) -> 5 | J8: =SUM($G$4:G8)/SUM($G$4:$G$43) -> 0.3720667 | K8: =MAX(0,(Assumptions!$B$7*D8-G8)/(1-Assumptions!$B$7))/D8 -> 0
A9: C015 | B9: =INDEX(Customers!$B$2:$B$41,MATCH(A9,Customers!$A$2:$A$41,0)) -> Specialty Chemicals | C9: =INDEX(Customers!$C$2:$C$41,MATCH(A9,Customers!$A$2:$A$41,0)) -> Strategic | D9: =SUMIFS(Transactions!$N$2:$N$2881,Transactions!$C$2:$C$2881,$A9,Transactions!$A$2:$A$2881,"2026") -> 7473582.7 | E9: =SUMIFS(Transactions!$P$2:$P$2881,Transactions!$C$2:$C$2881,$A9,Transactions!$A$2:$A$2881,"2026") -> 2992761.3 | F9: =INDEX(Customers!$J$2:$J$41,MATCH(A9,Customers!$A$2:$A$41,0)) -> 923000 | G9: =E9-F9 -> 2069761.3 | H9: =IFERROR(G9/D9,0) -> 0.27694365 | I9: =RANK(G9,$G$4:$G$43) -> 6 | J9: =SUM($G$4:G9)/SUM($G$4:$G$43) -> 0.43513348 | K9: =MAX(0,(Assumptions!$B$7*D9-G9)/(1-Assumptions!$B$7))/D9 -> 0
A10: C030 | B10: =INDEX(Customers!$B$2:$B$41,MATCH(A10,Customers!$A$2:$A$41,0)) -> Specialty Chemicals | C10: =INDEX(Customers!$C$2:$C$41,MATCH(A10,Customers!$A$2:$A$41,0)) -> Strategic | D10: =SUMIFS(Transactions!$N$2:$N$2881,Transactions!$C$2:$C$2881,$A10,Transactions!$A$2:$A$2881,"2026") -> 7098130.9 | E10: =SUMIFS(Transactions!$P$2:$P$2881,Transactions!$C$2:$C$2881,$A10,Transactions!$A$2:$A$2881,"2026") -> 2654788.2 | F10: =INDEX(Customers!$J$2:$J$41,MATCH(A10,Customers!$A$2:$A$41,0)) -> 781000 | G10: =E10-F10 -> 1873788.2 | H10: =IFERROR(G10/D10,0) -> 0.26398332 | I10: =RANK(G10,$G$4:$G$43) -> 7 | J10: =SUM($G$4:G10)/SUM($G$4:$G$43) -> 0.49222885 | K10: =MAX(0,(Assumptions!$B$7*D10-G10)/(1-Assumptions!$B$7))/D10 -> 0
A11: C022 | B11: =INDEX(Customers!$B$2:$B$41,MATCH(A11,Customers!$A$2:$A$41,0)) -> Refining | C11: =INDEX(Customers!$C$2:$C$41,MATCH(A11,Customers!$A$2:$A$41,0)) -> Transactional | D11: =SUMIFS(Transactions!$N$2:$N$2881,Transactions!$C$2:$C$2881,$A11,Transactions!$A$2:$A$2881,"2026") -> 4539033.7 | E11: =SUMIFS(Transactions!$P$2:$P$2881,Transactions!$C$2:$C$2881,$A11,Transactions!$A$2:$A$2881,"2026") -> 1710374.6 | F11: =INDEX(Customers!$J$2:$J$41,MATCH(A11,Customers!$A$2:$A$41,0)) -> 156000 | G11: =E11-F11 -> 1554374.6 | H11: =IFERROR(G11/D11,0) -> 0.34244614 | I11: =RANK(G11,$G$4:$G$43) -> 8 | J11: =SUM($G$4:G11)/SUM($G$4:$G$43) -> 0.53959151 | K11: =MAX(0,(Assumptions!$B$7*D11-G11)/(1-Assumptions!$B$7))/D11 -> 0
A12: C021 | B12: =INDEX(Customers!$B$2:$B$41,MATCH(A12,Customers!$A$2:$A$41,0)) -> Refining | C12: =INDEX(Customers!$C$2:$C$41,MATCH(A12,Customers!$A$2:$A$41,0)) -> Transactional | D12: =SUMIFS(Transactions!$N$2:$N$2881,Transactions!$C$2:$C$2881,$A12,Transactions!$A$2:$A$2881,"2026") -> 3803582 | E12: =SUMIFS(Transactions!$P$2:$P$2881,Transactions!$C$2:$C$2881,$A12,Transactions!$A$2:$A$2881,"2026") -> 1759839.5 | F12: =INDEX(Customers!$J$2:$J$41,MATCH(A12,Customers!$A$2:$A$41,0)) -> 358000 | G12: =E12-F12 -> 1401839.5 | H12: =IFERROR(G12/D12,0) -> 0.36855772 | I12: =RANK(G12,$G$4:$G$43) -> 9 | J12: =SUM($G$4:G12)/SUM($G$4:$G$43) -> 0.58230634 | K12: =MAX(0,(Assumptions!$B$7*D12-G12)/(1-Assumptions!$B$7))/D12 -> 0
A13: C016 | B13: =INDEX(Customers!$B$2:$B$41,MATCH(A13,Customers!$A$2:$A$41,0)) -> Refining | C13: =INDEX(Customers!$C$2:$C$41,MATCH(A13,Customers!$A$2:$A$41,0)) -> Transactional | D13: =SUMIFS(Transactions!$N$2:$N$2881,Transactions!$C$2:$C$2881,$A13,Transactions!$A$2:$A$2881,"2026") -> 4029731.7 | E13: =SUMIFS(Transactions!$P$2:$P$2881,Transactions!$C$2:$C$2881,$A13,Transactions!$A$2:$A$2881,"2026") -> 1622595.9 | F13: =INDEX(Customers!$J$2:$J$41,MATCH(A13,Customers!$A$2:$A$41,0)) -> 355000 | G13: =E13-F13 -> 1267595.9 | H13: =IFERROR(G13/D13,0) -> 0.31456088 | I13: =RANK(G13,$G$4:$G$43) -> 10 | J13: =SUM($G$4:G13)/SUM($G$4:$G$43) -> 0.6209307 | K13: =MAX(0,(Assumptions!$B$7*D13-G13)/(1-Assumptions!$B$7))/D13 -> 0
A14: C025 | B14: =INDEX(Customers!$B$2:$B$41,MATCH(A14,Customers!$A$2:$A$41,0)) -> Refining | C14: =INDEX(Customers!$C$2:$C$41,MATCH(A14,Customers!$A$2:$A$41,0)) -> Core | D14: =SUMIFS(Transactions!$N$2:$N$2881,Transactions!$C$2:$C$2881,$A14,Transactions!$A$2:$A$2881,"2026") -> 4371153.6 | E14: =SUMIFS(Transactions!$P$2:$P$2881,Transactions!$C$2:$C$2881,$A14,Transactions!$A$2:$A$2881,"2026") -> 1772249.4 | F14: =INDEX(Customers!$J$2:$J$41,MATCH(A14,Customers!$A$2:$A$41,0)) -> 611000 | G14: =E14-F14 -> 1161249.4 | H14: =IFERROR(G14/D14,0) -> 0.265662 | I14: =RANK(G14,$G$4:$G$43) -> 11 | J14: =SUM($G$4:G14)/SUM($G$4:$G$43) -> 0.65631461 | K14: =MAX(0,(Assumptions!$B$7*D14-G14)/(1-Assumptions!$B$7))/D14 -> 0
A15: C010 | B15: =INDEX(Customers!$B$2:$B$41,MATCH(A15,Customers!$A$2:$A$41,0)) -> Refining | C15: =INDEX(Customers!$C$2:$C$41,MATCH(A15,Customers!$A$2:$A$41,0)) -> Transactional | D15: =SUMIFS(Transactions!$N$2:$N$2881,Transactions!$C$2:$C$2881,$A15,Transactions!$A$2:$A$2881,"2026") -> 3355010.2 | E15: =SUMIFS(Transactions!$P$2:$P$2881,Transactions!$C$2:$C$2881,$A15,Transactions!$A$2:$A$2881,"2026") -> 1374666.3 | F15: =INDEX(Customers!$J$2:$J$41,MATCH(A15,Customers!$A$2:$A$41,0)) -> 237000 | G15: =E15-F15 -> 1137666.3 | H15: =IFERROR(G15/D15,0) -> 0.33909474 | I15: =RANK(G15,$G$4:$G$43) -> 12 | J15: =SUM($G$4:G15)/SUM($G$4:$G$43) -> 0.69097994 | K15: =MAX(0,(Assumptions!$B$7*D15-G15)/(1-Assumptions!$B$7))/D15 -> 0
... A43: C027 | B43: =INDEX(Customers!$B$2:$B$41,MATCH(A43,Customers!$A$2:$A$41,0)) -> Specialty Chemicals | C43: =INDEX(Customers!$C$2:$C$41,MATCH(A43,Customers!$A$2:$A$41,0)) -> Strategic | D43: =SUMIFS(Transactions!$N$2:$N$2881,Transactions!$C$2:$C$2881,$A43,Transactions!$A$2:$A$2881,"2026") -> 5935280.4 | E43: =SUMIFS(Transactions!$P$2:$P$2881,Transactions!$C$2:$C$2881,$A43,Transactions!$A$2:$A$2881,"2026") -> 1035422.1 | F43: =INDEX(Customers!$J$2:$J$41,MATCH(A43,Customers!$A$2:$A$41,0)) -> 1354000 | G43: =E43-F43 -> -318577.87 | H43: =IFERROR(G43/D43,0) -> -0.053675285 | I43: =RANK(G43,$G$4:$G$43) -> 40 | J43: =SUM($G$4:G43)/SUM($G$4:$G$43) -> 1 | K43: =MAX(0,(Assumptions!$B$7*D43-G43)/(1-Assumptions!$B$7))/D43 -> 0.40490038
A45: Total customers | H45: =COUNTA(A4:A43) -> 40
A46: Customers with negative net profit | H46: =COUNTIF(G4:G43,"<0") -> 6
A47: Customers below target net margin | H47: =COUNTIF(H4:H43,"<"&Assumptions!B7) -> 24
A48: Peak cumulative profit (whale curve) | H48: =MAX(J4:J43) -> 1.0217315
A49: Customers needed to reach peak profit | H49: =MATCH(MAX(J4:J43),J4:J43,0) -> 34
A50: Profit erased by loss-making customers | H50: =-SUMIF(G4:G43,"<0") -> 713196.98
A51: Total customer net profit | H51: =SUM(G4:G43) -> 32818565
A52: Pocket revenue at risk (below target) | H52: =SUMIF(H4:H43,"<"&Assumptions!B7,D4:D43) -> 63727185
A53: Avg price uplift needed (below-target customers) | H53: =IFERROR(SUMPRODUCT((H4:H43<Assumptions!B7)*K4:K43*D4:D43)/H52,0) -> 0.15852048
